README.txt
setup.py
collective/__init__.py
collective.megaphonesql.egg-info/PKG-INFO
collective.megaphonesql.egg-info/SOURCES.txt
collective.megaphonesql.egg-info/dependency_links.txt
collective.megaphonesql.egg-info/entry_points.txt
collective.megaphonesql.egg-info/namespace_packages.txt
collective.megaphonesql.egg-info/not-zip-safe
collective.megaphonesql.egg-info/paster_plugins.txt
collective.megaphonesql.egg-info/requires.txt
collective.megaphonesql.egg-info/top_level.txt
collective/megaphonesql/__init__.py
collective/megaphonesql/configure.zcml
collective/megaphonesql/tests.py
collective/megaphonesql/profiles/default/metadata.xml
collective/megaphonesql/profiles/default/types.xml
collective/megaphonesql/profiles/default/types/Action_Letter.xml
collective/megaphonesql/profiles/default/types/Megaphone_Action.xml
docs/HISTORY.txt
docs/INSTALL.txt
docs/LICENSE.GPL
docs/LICENSE.txt