Metadata-Version: 1.0
Name: collective.megaphonesql
Version: 0.1a1
Summary: Use Products.sqlpfgadapter in collective.megaphone
Home-page: http://svn.plone.org/svn/collective/
Author: Kees Hink
Author-email: hink@gw20e.com
License: GPL
Keywords: web plone sql
Platform: UNKNOWN
Classifier: Framework :: Plone
Classifier: Programming Language :: Python
